{
  "generated_at": "2026-04-30T10:50:10.294516",
  "count": 3,
  "games": [
    {
      "game_date": "2026-04-30",
      "game_time": "23:00",
      "home_team": "Atlanta Hawks",
      "away_team": "New York Knicks",
      "home_team_id": 1610612737,
      "away_team_id": 1610612752,
      "prediction": {
        "home_win_prob": 0.474,
        "away_win_prob": 0.526,
        "confidence": "Toss-Up",
        "favored": "away"
      },
      "context": {
        "home_elo": 1417.1,
        "away_elo": 1545.1,
        "home_recent_wins": 0.5,
        "away_recent_wins": 0.4,
        "home_rest_days": 14,
        "away_rest_days": 14,
        "home_b2b": false,
        "away_b2b": false
      }
    },
    {
      "game_date": "2026-05-01",
      "game_time": "00:00",
      "home_team": "Philadelphia 76ers",
      "away_team": "Boston Celtics",
      "home_team_id": 1610612755,
      "away_team_id": 1610612738,
      "prediction": {
        "home_win_prob": 0.436,
        "away_win_prob": 0.564,
        "confidence": "Lean Underdog",
        "favored": "away"
      },
      "context": {
        "home_elo": 1458.0,
        "away_elo": 1613.9,
        "home_recent_wins": 0.5,
        "away_recent_wins": 0.6,
        "home_rest_days": 14,
        "away_rest_days": 14,
        "home_b2b": false,
        "away_b2b": false
      }
    },
    {
      "game_date": "2026-05-01",
      "game_time": "01:30",
      "home_team": "Minnesota Timberwolves",
      "away_team": "Denver Nuggets",
      "home_team_id": 1610612750,
      "away_team_id": 1610612743,
      "prediction": {
        "home_win_prob": 0.549,
        "away_win_prob": 0.451,
        "confidence": "Toss-Up",
        "favored": "home"
      },
      "context": {
        "home_elo": 1480.8,
        "away_elo": 1579.1,
        "home_recent_wins": 0.5,
        "away_recent_wins": 0.8,
        "home_rest_days": 14,
        "away_rest_days": 14,
        "home_b2b": false,
        "away_b2b": false
      }
    }
  ]
}